sakku/__init__.py
sakku/application.py
sakku/catalog.py
sakku/config.py
sakku/consts.py
sakku/domain.py
sakku/exceptions.py
sakku/json_schema.json
sakku/json_schema.py
sakku/network.py
sakku/request_handler.py
sakku/response_handler.py
sakku/sakku.py
sakku/version.py
pod_sakku-1.0.0.dist-info/METADATA
pod_sakku-1.0.0.dist-info/WHEEL
pod_sakku-1.0.0.dist-info/top_level.txt
pod_sakku-1.0.0.dist-info/RECORD
